locals3server/__init__.py
locals3server/__main__.py
locals3server/actions.py
locals3server/errors.py
locals3server/fastapi_server.py
locals3server/file_store.py
locals3server/models.py
locals3server/xml_templates.py
local_s3_server-0.2.2.dist-info/METADATA
local_s3_server-0.2.2.dist-info/WHEEL
local_s3_server-0.2.2.dist-info/entry_points.txt
local_s3_server-0.2.2.dist-info/RECORD
