Metadata-Version: 2.4
Name: local-s3-server
Version: 0.2.2
Summary: A lightweight, FastAPI-based S3-compatible server for local development and testing
Project-URL: Homepage, https://github.com/oeway/local-s3-server
Project-URL: Repository, https://github.com/oeway/local-s3-server.git
Author-email: Wei Ouyang <oeway007@gmail.com>
License: MIT
Keywords: development,fastapi,mock,s3,testing
Classifier: Development Status :: 3 - Alpha
Classifier: Intended Audience :: Developers
Classifier: License :: OSI Approved :: MIT License
Classifier: Programming Language :: Python :: 3
Classifier: Programming Language :: Python :: 3.7
Classifier: Programming Language :: Python :: 3.8
Classifier: Programming Language :: Python :: 3.9
Classifier: Programming Language :: Python :: 3.10
Classifier: Programming Language :: Python :: 3.11
Requires-Python: >=3.7
Requires-Dist: fastapi>=0.68.0
Requires-Dist: python-multipart>=0.0.5
Requires-Dist: uvicorn>=0.15.0
Provides-Extra: dev
Requires-Dist: black>=21.0; extra == 'dev'
Requires-Dist: flake8>=3.9; extra == 'dev'
Requires-Dist: isort>=5.0; extra == 'dev'
Requires-Dist: mypy>=0.910; extra == 'dev'
Requires-Dist: pytest-cov>=2.0; extra == 'dev'
Requires-Dist: pytest>=6.0; extra == 'dev'
